LICENSE
MANIFEST.in
Makefile
setup.py
Flask_GAE_Mini_Profiler.egg-info/PKG-INFO
Flask_GAE_Mini_Profiler.egg-info/SOURCES.txt
Flask_GAE_Mini_Profiler.egg-info/dependency_links.txt
Flask_GAE_Mini_Profiler.egg-info/namespace_packages.txt
Flask_GAE_Mini_Profiler.egg-info/not-zip-safe
Flask_GAE_Mini_Profiler.egg-info/requires.txt
Flask_GAE_Mini_Profiler.egg-info/top_level.txt
docs/.gitignore
docs/Makefile
docs/conf.py
docs/index.rst
docs/make.bat
docs/_static/profiler1.png
flaskext/__init__.py
flaskext/gae_mini_profiler/__init__.py
flaskext/gae_mini_profiler/profiler.py
flaskext/gae_mini_profiler/static/css/profiler.css
flaskext/gae_mini_profiler/static/js/profiler.js
flaskext/gae_mini_profiler/static/js/template.tmpl
flaskext/gae_mini_profiler/templates/includes.html
flaskext/gae_mini_profiler/templates/shared.html
tests/__init__.py
tests/extension.py
tests/gaemock/google/__init__.py
tests/gaemock/google/appengine/__init__.py
tests/gaemock/google/appengine/api.py
tests/gaemock/google/appengine/ext/__init__.py
tests/gaemock/google/appengine/ext/webapp.py