Metadata-Version: 1.0
Name: Flask-GAE-Mini-Profiler
Version: 0.1.2
Summary: Flask integration of gae_mini_profiler
Home-page: http://packages.python.org/Flask-GAE-Mini-Profiler
Author: Pascal Hartig
Author-email: phartig@rdrei.net
License: MIT
Platform: any
Classifier: Development Status :: 4 - Beta
Classifier: Environment :: Web Environment
Classifier: Intended Audience :: Developers
Classifier: License :: OSI Approved :: MIT License
Classifier: Operating System :: OS Independent
Classifier: Programming Language :: Python
Classifier: Topic :: Internet :: WWW/HTTP :: Dynamic Content
Classifier: Topic :: Software Development :: Libraries :: Python Modules
